MANIFEST.in
README.rst
setup.py
docs/HISTORY.txt
docs/INSTALL.txt
docs/LICENSE.GPL
docs/LICENSE.txt
docs/TODO.txt
unice/.DS_Store
unice/__init__.py
unice.portlet.slider.egg-info/PKG-INFO
unice.portlet.slider.egg-info/SOURCES.txt
unice.portlet.slider.egg-info/dependency_links.txt
unice.portlet.slider.egg-info/entry_points.txt
unice.portlet.slider.egg-info/namespace_packages.txt
unice.portlet.slider.egg-info/not-zip-safe
unice.portlet.slider.egg-info/requires.txt
unice.portlet.slider.egg-info/top_level.txt
unice/portlet/.DS_Store
unice/portlet/__init__.py
unice/portlet/slider/.DS_Store
unice/portlet/slider/__init__.py
unice/portlet/slider/configure.zcml
unice/portlet/slider/sliderportlet.pt
unice/portlet/slider/sliderportlet.py
unice/portlet/slider/vocabularies.py
unice/portlet/slider/browser/.DS_Store
unice/portlet/slider/browser/__init__.py
unice/portlet/slider/browser/configure.zcml
unice/portlet/slider/browser/images/.DS_Store
unice/portlet/slider/browser/images/controls.psd
unice/portlet/slider/browser/javascripts/.DS_Store
unice/portlet/slider/browser/javascripts/scripts.js
unice/portlet/slider/browser/stylesheets/.DS_Store
unice/portlet/slider/browser/stylesheets/jquery.bxslider.css
unice/portlet/slider/browser/stylesheets/styles.css
unice/portlet/slider/browser/stylesheets/images/bx_loader.gif
unice/portlet/slider/browser/stylesheets/images/controls.png
unice/portlet/slider/profiles/.DS_Store
unice/portlet/slider/profiles/default/cssregistry.xml
unice/portlet/slider/profiles/default/jsregistry.xml
unice/portlet/slider/profiles/default/metadata.xml
unice/portlet/slider/profiles/default/portlets.xml
unice/portlet/slider/tests/__init__.py
unice/portlet/slider/tests/base.py
unice/portlet/slider/tests/test_portlet.py